install/__init__.py
install/__main__.py
install/_vendor/__init__.py
install/_vendor/installer/noxfile.py
install/_vendor/installer/src/installer/__init__.py
install/_vendor/installer/src/installer/records.py
install/_vendor/installer/src/installer/scripts.py
install/_vendor/installer/src/installer/_compat/__init__.py
install/_vendor/installer/src/installer/_compat/importlib_resources.py
install/_vendor/installer/src/installer/_compat/typing.py
install/_vendor/installer/src/installer/_scripts/__init__.py
python_install-0.0.3.dist-info/LICENSE
python_install-0.0.3.dist-info/METADATA
python_install-0.0.3.dist-info/WHEEL
python_install-0.0.3.dist-info/top_level.txt
python_install-0.0.3.dist-info/RECORD
