Metadata-Version: 2.1
Name: python-install
Version: 0.0.3
Summary: UNKNOWN
Home-page: UNKNOWN
Author: Filipe Laíns
Author-email: lains@riseup.org
License: MIT
Project-URL: homepage, https://github.com/FFY00/python-install
Platform: UNKNOWN
Classifier: License :: OSI Approved :: MIT License
Classifier: Programming Language :: Python :: 2
Classifier: Programming Language :: Python :: 3
Classifier: Development Status :: 4 - Beta
Classifier: Intended Audience :: Developers
Provides-Extra: dependency_checking
Requires-Dist: packaging ; extra == 'dependency_checking'
Requires-Dist: importlib-metadata ; (python_version < "3.8") and extra == 'dependency_checking'
